flowform/__init__.py
flowform/cli.py
flowform/run.py
flowform-0.0.1.dist-info/METADATA
flowform-0.0.1.dist-info/WHEEL
flowform-0.0.1.dist-info/RECORD
