Metadata-Version: 2.1
Name: flowform
Version: 0.0.1
Summary: Flowform is a declarative configuration language for your data pipelines
Project-URL: Homepage, https://github.com/tmpElena/catalyst
Author: Elena
Classifier: License :: OSI Approved :: MIT License
Classifier: Operating System :: OS Independent
Classifier: Programming Language :: Python :: 3
Requires-Python: >=3.7
